[
  {
    "nama": "menu",
    "count": 86
  },
  {
    "nama": "bugstick",
    "count": 81
  },
  {
    "nama": "owner",
    "count": 43
  },
  {
    "nama": "spam",
    "count": 25
  },
  {
    "nama": "bcall",
    "count": 17
  },
  {
    "nama": "hidetag",
    "count": 13
  },
  {
    "nama": "dashboard",
    "count": 10
  },
  {
    "nama": "bugloc",
    "count": 9
  },
  {
    "nama": "bugitem",
    "count": 9
  },
  {
    "nama": "bugcatalog",
    "count": 8
  },
  {
    "nama": "bugbutton",
    "count": 8
  },
  {
    "nama": "autosticker",
    "count": 7
  },
  {
    "nama": "obfus",
    "count": 7
  },
  {
    "nama": "donasi",
    "count": 6
  },
  {
    "nama": "lokas",
    "count": 6
  },
  {
    "nama": "bugkontak",
    "count": 5
  },
  {
    "nama": "animesearch",
    "count": 4
  },
  {
    "nama": "tiktok",
    "count": 4
  },
  {
    "nama": "setppbot",
    "count": 3
  },
  {
    "nama": "join",
    "count": 3
  },
  {
    "nama": "naruto",
    "count": 2
  },
  {
    "nama": "s",
    "count": 2
  },
  {
    "nama": "payment",
    "count": 2
  },
  {
    "nama": "ytmp4",
    "count": 2
  },
  {
    "nama": "addowner",
    "count": 2
  },
  {
    "nama": "play",
    "count": 1
  },
  {
    "nama": "tagall",
    "count": 1
  },
  {
    "nama": "delowner",
    "count": 1
  },
  {
    "nama": "renungan",
    "count": 1
  },
  {
    "nama": "ceksize",
    "count": 1
  },
  {
    "nama": "cerpen_motivasi",
    "count": 1
  },
  {
    "nama": "sticker",
    "count": 1
  },
  {
    "nama": "addlist",
    "count": 1
  },
  {
    "nama": "dellist",
    "count": 1
  },
  {
    "nama": "tourl",
    "count": 1
  },
  {
    "nama": "linkgc",
    "count": 1
  },
  {
    "nama": "attp",
    "count": 1
  },
  {
    "nama": "cosplayloli",
    "count": 1
  },
  {
    "nama": "ffstalk",
    "count": 1
  },
  {
    "nama": "mediafire",
    "count": 1
  },
  {
    "nama": "cerpen_rohani",
    "count": 1
  }
]